{
  "result": {
    "uuid": "a755a6d1-fc4a-4961-a8cc-b2293fe5b81c",
    "name": "Eligendi ipsa quia qui laudantium dicta.",
    "email": "Gunnar.Kreiger@gmail.com",
    "nickname": "Et odio dolor quibusdam cupiditate sed exercitationem harum mollitia explicabo."
  },

  "fields": {
    "name": {
      "name": "name",
      "type": "text"
    },
    "email": {
      "name": "email",
      "type": "email"
    },
    "nickname": {
      "name": "nickname",
      "type": "text"
    }
  },

  "status": {
    "code": 200
  }
}
